amarettopy/__init__.py
amarettopy/calib.py
amarettopy/const.py
amarettopy/lib.py
amarettopy/path.py
amarettopy/cli/__init__.py
amarettopy/cli/amrtctl.py
amarettopy/gui/__init__.py
amarettopy/gui/amrtctl.py
amarettopy/gui/config_tab.py
amarettopy/gui/graph_tab.py
amarettopy/gui/init_tab.py
amarettopy/gui/log_tab.py
amarettopy/gui/main_panel.py
amarettopy/gui/side_panel.py
amarettopy/gui/top_panel.py
amarettopy/gui/util.py
amarettopy/gui/config/default_params.yml
amarettopy/gui/config/params_sample.yml
amarettopy/gui/config/servo.yml
amarettopy/gui/config/system.yml
amarettopy/gui/imgs/LED-GREEN.gif
amarettopy/gui/imgs/LED-OFF.gif
amarettopy/gui/imgs/LED-RED.gif
amarettopy-0.1.0.dist-info/METADATA
amarettopy-0.1.0.dist-info/RECORD
amarettopy-0.1.0.dist-info/WHEEL
amarettopy-0.1.0.dist-info/entry_points.txt
amarettopy-0.1.0.dist-info/top_level.txt
