Metadata-Version: 2.1
Name: amarettopy
Version: 0.1.0
Summary: python API for Buildit Actuator
Home-page: https://github.com/Smartrobotics/AmarettoPy
Author: SR
Author-email: sr-dev@smartrobotics.jp
License: UNKNOWN
Platform: UNKNOWN
Classifier: Programming Language :: Python :: 3
Classifier: License :: OSI Approved :: MIT License
Classifier: Operating System :: OS Independent
Requires-Dist: crc8
Requires-Dist: numpy
Requires-Dist: pyserial
Requires-Dist: matplotlib
Requires-Dist: numpy
Requires-Dist: pyyaml
